imppkg/HarmonicMean.py
imppkg/__init__.py
imppkg/hello.c
imppkg/hello.cp310-win_amd64.pyd
imppkg/hello.pyx
app1_akshay_kumar-0.1.0.dist-info/METADATA
app1_akshay_kumar-0.1.0.dist-info/WHEEL
app1_akshay_kumar-0.1.0.dist-info/entry_points.txt
app1_akshay_kumar-0.1.0.dist-info/top_level.txt
app1_akshay_kumar-0.1.0.dist-info/RECORD
