Metadata-Version: 2.1
Name: app1-akshay-kumar
Version: 0.1.0
Summary: Application Visibility
Author: Akshay Kumar
Author-email: akshay.kumar4@hpe.com
Requires-Python: >=3.8
Requires-Dist: termcolor (<2,>=1.1.0)
